{
 "title": "Spørgeskema",
 "pages": [
  {
   "name": "page1",
   "elements": [
    {
     "type": "dropdown",
     "name": "question1",
     "title": "Hvad er dit køn?",
     "choices": [
      {
       "value": "item1",
       "text": "Female"
      },
      {
       "value": "item2",
       "text": "Male"
      },
      {
       "value": "item3",
       "text": "Other"
      }
     ]
    },
    {
     "type": "text",
     "name": "question2",
     "title": "Hvor gammel er du?",
     "inputType": "number"
    },
    {
     "type": "text",
     "name": "question3",
     "title": "Hvor mange hjalp dig med at spille?",
     "inputType": "number",
     "placeHolder": "1"
    }
   ]
  }
 ]
}
